HISTORY.txt
README.txt
ez_setup.py
setup.cfg
setup.py
src/ClueBin.egg-info/PKG-INFO
src/ClueBin.egg-info/SOURCES.txt
src/ClueBin.egg-info/dependency_links.txt
src/ClueBin.egg-info/entry_points.txt
src/ClueBin.egg-info/not-zip-safe
src/ClueBin.egg-info/requires.txt
src/ClueBin.egg-info/top_level.txt
src/cluebin/__init__.py
src/cluebin/googledata.py
src/cluebin/paste.py
src/cluebin/pastebin.py
src/cluebin/sqldata.py
src/cluebin/tests.py
src/cluebin/utils.py