Metadata-Version: 1.0
Name: ClueBin
Version: 0.2.2
Summary: Pastebin application
Home-page: UNKNOWN
Author: Rocky Burt
Author-email: rocky@serverzen.com
License: UNKNOWN
Platform: UNKNOWN
Classifier: Programming Language :: Python
Classifier: Topic :: Software Development :: Libraries :: Python Modules
